{
    "bangumi_id": "6",
    "episodes": [
        {
            "resources": [
                {
                    "share_dmhy_org": {
                        "magnet": {
                            "url": "magnet:?xt=urn:btih:OMIBEFIWF7MBAP7PMBHUDBO5S5JKUYOJ&tr=http%3A%2F%2F104.143.10.186%3A8000%2Fannounce&tr=udp%3A%2F%2F104.143.10.186%3A8000%2Fannounce&tr=http%3A%2F%2Ftracker.openbittorrent.com%3A80%2Fannounce&tr=http%3A%2F%2Ftracker3.itzmx.com%3A6961%2Fannounce&tr=http%3A%2F%2Ftracker4.itzmx.com%3A2710%2Fannounce"
                        },
                        "author": "jiaoloveKT",
                        "publish_timestamp": "1712560717",
                        "title": "【极影字幕社】★4月新番 狼与香辛料 行商邂逅贤狼/Ookami to Koushinryou: Merchant Meets the Wise Wolf 第01v2话 GB 720P MP4（字幕社招人内详）",
                        "page_link": "http://share.dmhy.org/topics/view/666558_4_Ookami_to_Koushinryou_Merchant_Meets_the_Wise_Wolf_01v2_GB_720P_MP4.html",
                        "tags": [
                            {
                                "tag": "720P"
                            },
                            {
                                "tag": "GB"
                            },
                            {
                                "tag": "MP4"
                            },
                            {
                                "tag": "字幕社招人内详"
                            },
                            {
                                "tag": "极影字幕社"
                            }
                        ]
                    }
                },
                {
                    "share_dmhy_org": {
                        "magnet": {
                            "url": "magnet:?xt=urn:btih:M7XBNYFMTR47YQ3LF35LQDCZXSI22ABX&tr=http%3A%2F%2F104.143.10.186%3A8000%2Fannounce&tr=udp%3A%2F%2F104.143.10.186%3A8000%2Fannounce&tr=http%3A%2F%2Ftracker.openbittorrent.com%3A80%2Fannounce&tr=http%3A%2F%2Ftracker3.itzmx.com%3A6961%2Fannounce&tr=http%3A%2F%2Ftracker4.itzmx.com%3A2710%2Fannounce"
                        },
                        "author": "jiaoloveKT",
                        "publish_timestamp": "1712560742",
                        "title": "【极影字幕社】★4月新番 狼与香辛料 行商邂逅贤狼/Ookami to Koushinryou: Merchant Meets the Wise Wolf 第01v2话 GB 1080P MP4（字幕社招人内详）",
                        "page_link": "http://share.dmhy.org/topics/view/666559_4_Ookami_to_Koushinryou_Merchant_Meets_the_Wise_Wolf_01v2_GB_1080P_MP4.html",
                        "tags": [
                            {
                                "tag": "1080P"
                            },
                            {
                                "tag": "GB"
                            },
                            {
                                "tag": "MP4"
                            },
                            {
                                "tag": "字幕社招人内详"
                            },
                            {
                                "tag": "极影字幕社"
                            }
                        ]
                    }
                },
                {
                    "share_dmhy_org": {
                        "magnet": {
                            "url": "magnet:?xt=urn:btih:SIG2KX42L6C445DYNLXEYN3GJ5IKJHFO&tr=http%3A%2F%2F104.143.10.186%3A8000%2Fannounce&tr=udp%3A%2F%2F104.143.10.186%3A8000%2Fannounce&tr=http%3A%2F%2Ftracker.openbittorrent.com%3A80%2Fannounce&tr=http%3A%2F%2Ftracker3.itzmx.com%3A6961%2Fannounce&tr=http%3A%2F%2Ftracker4.itzmx.com%3A2710%2Fannounce"
                        },
                        "author": "jiaoloveKT",
                        "publish_timestamp": "1713055896",
                        "title": "【極影字幕社】★4月新番 狼與香辛料 行商邂逅賢狼/Ookami to Koushinryou: Merchant Meets the Wise Wolf 第01v2話 BIG5 720P MP4（字幕社招人內詳）",
                        "page_link": "http://share.dmhy.org/topics/view/667167_4_Ookami_to_Koushinryou_Merchant_Meets_the_Wise_Wolf_01v2_BIG5_720P_MP4.html",
                        "tags": [
                            {
                                "tag": "720P"
                            },
                            {
                                "tag": "BIG5"
                            },
                            {
                                "tag": "MP4"
                            },
                            {
                                "tag": "字幕社招人內詳"
                            },
                            {
                                "tag": "極影字幕社"
                            }
                        ]
                    }
                },
                {
                    "share_dmhy_org": {
                        "magnet": {
                            "url": "magnet:?xt=urn:btih:ZQUSGIVZ4V5I7LHEMFWNEUTNM2FEH4SA&tr=http%3A%2F%2F104.143.10.186%3A8000%2Fannounce&tr=udp%3A%2F%2F104.143.10.186%3A8000%2Fannounce&tr=http%3A%2F%2Ftracker.openbittorrent.com%3A80%2Fannounce&tr=http%3A%2F%2Ftracker3.itzmx.com%3A6961%2Fannounce&tr=http%3A%2F%2Ftracker4.itzmx.com%3A2710%2Fannounce"
                        },
                        "author": "jiaoloveKT",
                        "publish_timestamp": "1713055947",
                        "title": "【極影字幕社】★4月新番 狼與香辛料 行商邂逅賢狼/Ookami to Koushinryou: Merchant Meets the Wise Wolf 第01v2話 BIG5 1080P MP4（字幕社招人內詳）",
                        "page_link": "http://share.dmhy.org/topics/view/667168_4_Ookami_to_Koushinryou_Merchant_Meets_the_Wise_Wolf_01v2_BIG5_1080P_MP4.html",
                        "tags": [
                            {
                                "tag": "1080P"
                            },
                            {
                                "tag": "BIG5"
                            },
                            {
                                "tag": "MP4"
                            },
                            {
                                "tag": "字幕社招人內詳"
                            },
                            {
                                "tag": "極影字幕社"
                            }
                        ]
                    }
                }
            ]
        },
        {
            "index": "01",
            "resources": [
                {
                    "share_dmhy_org": {
                        "magnet": {
                            "url": "magnet:?xt=urn:btih:TAJ2PCWS77DYPSMNN7FGXUKFYLWBCNTG&tr=http%3A%2F%2F104.143.10.186%3A8000%2Fannounce&tr=udp%3A%2F%2F104.143.10.186%3A8000%2Fannounce&tr=http%3A%2F%2Ftracker.openbittorrent.com%3A80%2Fannounce&tr=http%3A%2F%2Ftracker3.itzmx.com%3A6961%2Fannounce&tr=http%3A%2F%2Ftracker4.itzmx.com%3A2710%2Fannounce"
                        },
                        "author": "zhufeng",
                        "publish_timestamp": "1712046560",
                        "title": "【幻之字幕组】狼与香辛料 行商邂逅贤狼 01/狼と香辛料 MERCHANT MEETS THE WISE WOLF - 01 [简中][1080p][HEVC]",
                        "page_link": "http://share.dmhy.org/topics/view/665974_01_MERCHANT_MEETS_THE_WISE_WOLF_-_01_1080p_HEVC.html",
                        "tags": [
                            {
                                "tag": "1080P"
                            },
                            {
                                "tag": "HEVC"
                            },
                            {
                                "tag": "幻之字幕组"
                            },
                            {
                                "tag": "简中"
                            }
                        ]
                    }
                },
                {
                    "share_dmhy_org": {
                        "magnet": {
                            "url": "magnet:?xt=urn:btih:5C4APOJWLP5RV2DJELOAPGWMBSU6D5NA&tr=http%3A%2F%2F104.143.10.186%3A8000%2Fannounce&tr=udp%3A%2F%2F104.143.10.186%3A8000%2Fannounce&tr=http%3A%2F%2Ftracker.openbittorrent.com%3A80%2Fannounce&tr=http%3A%2F%2Ftracker3.itzmx.com%3A6961%2Fannounce&tr=http%3A%2F%2Ftracker4.itzmx.com%3A2710%2Fannounce"
                        },
                        "author": "KissSub",
                        "publish_timestamp": "1712262779",
                        "title": "[爱恋&漫猫字幕社][4月新番][狼与香辛料 行商邂逅贤狼][Spice and Wolf][01][720p][MP4][GB][简中]",
                        "page_link": "http://share.dmhy.org/topics/view/666139_4_Spice_and_Wolf_01_720p_MP4_GB.html",
                        "tags": [
                            {
                                "tag": "720P"
                            },
                            {
                                "tag": "GB"
                            },
                            {
                                "tag": "MP4"
                            },
                            {
                                "tag": "爱恋&漫猫字幕社"
                            },
                            {
                                "tag": "简中"
                            }
                        ]
                    }
                },
                {
                    "share_dmhy_org": {
                        "magnet": {
                            "url": "magnet:?xt=urn:btih:2YA6SAKOK2BQKNC2IKMGIDS2GTX7ZQAB&tr=http%3A%2F%2F104.143.10.186%3A8000%2Fannounce&tr=udp%3A%2F%2F104.143.10.186%3A8000%2Fannounce&tr=http%3A%2F%2Ftracker.openbittorrent.com%3A80%2Fannounce&tr=http%3A%2F%2Ftracker3.itzmx.com%3A6961%2Fannounce&tr=http%3A%2F%2Ftracker4.itzmx.com%3A2710%2Fannounce"
                        },
                        "author": "KissSub",
                        "publish_timestamp": "1712262800",
                        "title": "[爱恋&漫猫字幕社][4月新番][狼与香辛料 行商邂逅贤狼][Spice and Wolf][01][1080p][MP4][GB][简中]",
                        "page_link": "http://share.dmhy.org/topics/view/666141_4_Spice_and_Wolf_01_1080p_MP4_GB.html",
                        "tags": [
                            {
                                "tag": "1080P"
                            },
                            {
                                "tag": "GB"
                            },
                            {
                                "tag": "MP4"
                            },
                            {
                                "tag": "爱恋&漫猫字幕社"
                            },
                            {
                                "tag": "简中"
                            }
                        ]
                    }
                },
                {
                    "share_dmhy_org": {
                        "magnet": {
                            "url": "magnet:?xt=urn:btih:ZBS5AZOTOQJPLIO3DXUITV7QLWCWG62E&tr=http%3A%2F%2F104.143.10.186%3A8000%2Fannounce&tr=udp%3A%2F%2F104.143.10.186%3A8000%2Fannounce&tr=http%3A%2F%2Ftracker.openbittorrent.com%3A80%2Fannounce&tr=http%3A%2F%2Ftracker3.itzmx.com%3A6961%2Fannounce&tr=http%3A%2F%2Ftracker4.itzmx.com%3A2710%2Fannounce"
                        },
                        "author": "jiaoloveKT",
                        "publish_timestamp": "1712388139",
                        "title": "【极影字幕社】★4月新番 狼与香辛料 行商邂逅贤狼/Ookami to Koushinryou: Merchant Meets the Wise Wolf 第01话 GB 720P MP4（字幕社招人内详）",
                        "page_link": "http://share.dmhy.org/topics/view/666254_4_Ookami_to_Koushinryou_Merchant_Meets_the_Wise_Wolf_01_GB_720P_MP4.html",
                        "tags": [
                            {
                                "tag": "720P"
                            },
                            {
                                "tag": "GB"
                            },
                            {
                                "tag": "MP4"
                            },
                            {
                                "tag": "字幕社招人内详"
                            },
                            {
                                "tag": "极影字幕社"
                            }
                        ]
                    }
                },
                {
                    "share_dmhy_org": {
                        "magnet": {
                            "url": "magnet:?xt=urn:btih:GLK5NLYAHAQXHFTNS5EHH66774ZB5U4L&tr=http%3A%2F%2F104.143.10.186%3A8000%2Fannounce&tr=udp%3A%2F%2F104.143.10.186%3A8000%2Fannounce&tr=http%3A%2F%2Ftracker.openbittorrent.com%3A80%2Fannounce&tr=http%3A%2F%2Ftracker3.itzmx.com%3A6961%2Fannounce&tr=http%3A%2F%2Ftracker4.itzmx.com%3A2710%2Fannounce"
                        },
                        "author": "jiaoloveKT",
                        "publish_timestamp": "1712388187",
                        "title": "【极影字幕社】★4月新番 狼与香辛料 行商邂逅贤狼/Ookami to Koushinryou: Merchant Meets the Wise Wolf 第01话 GB 1080P MP4（字幕社招人内详）",
                        "page_link": "http://share.dmhy.org/topics/view/666255_4_Ookami_to_Koushinryou_Merchant_Meets_the_Wise_Wolf_01_GB_1080P_MP4.html",
                        "tags": [
                            {
                                "tag": "1080P"
                            },
                            {
                                "tag": "GB"
                            },
                            {
                                "tag": "MP4"
                            },
                            {
                                "tag": "字幕社招人内详"
                            },
                            {
                                "tag": "极影字幕社"
                            }
                        ]
                    }
                },
                {
                    "share_dmhy_org": {
                        "magnet": {
                            "url": "magnet:?xt=urn:btih:5OCOQYJ5ZE2NUVDZZ7VLJVDW4BZFVNBR&tr=http%3A%2F%2F104.143.10.186%3A8000%2Fannounce&tr=udp%3A%2F%2F104.143.10.186%3A8000%2Fannounce&tr=http%3A%2F%2Ftracker.openbittorrent.com%3A80%2Fannounce&tr=http%3A%2F%2Ftracker3.itzmx.com%3A6961%2Fannounce&tr=http%3A%2F%2Ftracker4.itzmx.com%3A2710%2Fannounce"
                        },
                        "author": "jiaoloveKT",
                        "publish_timestamp": "1712447618",
                        "title": "【極影字幕社】★4月新番 狼與香辛料 行商邂逅賢狼/Ookami to Koushinryou: Merchant Meets the Wise Wolf 第01話 BIG5 720P MP4（字幕社招人內詳）",
                        "page_link": "http://share.dmhy.org/topics/view/666309_4_Ookami_to_Koushinryou_Merchant_Meets_the_Wise_Wolf_01_BIG5_720P_MP4.html",
                        "tags": [
                            {
                                "tag": "720P"
                            },
                            {
                                "tag": "BIG5"
                            },
                            {
                                "tag": "MP4"
                            },
                            {
                                "tag": "字幕社招人內詳"
                            },
                            {
                                "tag": "極影字幕社"
                            }
                        ]
                    }
                },
                {
                    "share_dmhy_org": {
                        "magnet": {
                            "url": "magnet:?xt=urn:btih:FNSCE7UXDMZLQMU5RO2AYQRMUUAQBPGJ&tr=http%3A%2F%2F104.143.10.186%3A8000%2Fannounce&tr=udp%3A%2F%2F104.143.10.186%3A8000%2Fannounce&tr=http%3A%2F%2Ftracker.openbittorrent.com%3A80%2Fannounce&tr=http%3A%2F%2Ftracker3.itzmx.com%3A6961%2Fannounce&tr=http%3A%2F%2Ftracker4.itzmx.com%3A2710%2Fannounce"
                        },
                        "author": "jiaoloveKT",
                        "publish_timestamp": "1712447686",
                        "title": "【極影字幕社】★4月新番 狼與香辛料 行商邂逅賢狼/Ookami to Koushinryou: Merchant Meets the Wise Wolf 第01話 BIG5 1080P MP4（字幕社招人內詳）",
                        "page_link": "http://share.dmhy.org/topics/view/666310_4_Ookami_to_Koushinryou_Merchant_Meets_the_Wise_Wolf_01_BIG5_1080P_MP4.html",
                        "tags": [
                            {
                                "tag": "1080P"
                            },
                            {
                                "tag": "BIG5"
                            },
                            {
                                "tag": "MP4"
                            },
                            {
                                "tag": "字幕社招人內詳"
                            },
                            {
                                "tag": "極影字幕社"
                            }
                        ]
                    }
                }
            ]
        },
        {
            "index": "02",
            "resources": [
                {
                    "share_dmhy_org": {
                        "magnet": {
                            "url": "magnet:?xt=urn:btih:VRJ644GJKHCQTWI43FKYP4H43PAP4JYY&tr=http%3A%2F%2F104.143.10.186%3A8000%2Fannounce&tr=udp%3A%2F%2F104.143.10.186%3A8000%2Fannounce&tr=http%3A%2F%2Ftracker.openbittorrent.com%3A80%2Fannounce&tr=http%3A%2F%2Ftracker3.itzmx.com%3A6961%2Fannounce&tr=http%3A%2F%2Ftracker4.itzmx.com%3A2710%2Fannounce"
                        },
                        "author": "zhufeng",
                        "publish_timestamp": "1712619158",
                        "title": "【幻之字幕组】狼与香辛料 行商邂逅贤狼 02/狼と香辛料 MERCHANT MEETS THE WISE WOLF - 02 [简中][1080p][HEVC]",
                        "page_link": "http://share.dmhy.org/topics/view/666611_01_MERCHANT_MEETS_THE_WISE_WOLF_-_02_1080p_HEVC.html",
                        "tags": [
                            {
                                "tag": "1080P"
                            },
                            {
                                "tag": "HEVC"
                            },
                            {
                                "tag": "幻之字幕组"
                            },
                            {
                                "tag": "简中"
                            }
                        ]
                    }
                },
                {
                    "share_dmhy_org": {
                        "magnet": {
                            "url": "magnet:?xt=urn:btih:HXH6BE6CUENRQY56RAJDSD7YVUQEQAEC&tr=http%3A%2F%2F104.143.10.186%3A8000%2Fannounce&tr=udp%3A%2F%2F104.143.10.186%3A8000%2Fannounce&tr=http%3A%2F%2Ftracker.openbittorrent.com%3A80%2Fannounce&tr=http%3A%2F%2Ftracker3.itzmx.com%3A6961%2Fannounce&tr=http%3A%2F%2Ftracker4.itzmx.com%3A2710%2Fannounce"
                        },
                        "author": "jiaoloveKT",
                        "publish_timestamp": "1712993777",
                        "title": "【极影字幕社】★4月新番 狼与香辛料 行商邂逅贤狼/Ookami to Koushinryou: Merchant Meets the Wise Wolf 第02话 GB 720P MP4（字幕社招人内详）",
                        "page_link": "http://share.dmhy.org/topics/view/667065_4_Ookami_to_Koushinryou_Merchant_Meets_the_Wise_Wolf_02_GB_720P_MP4.html",
                        "tags": [
                            {
                                "tag": "720P"
                            },
                            {
                                "tag": "GB"
                            },
                            {
                                "tag": "MP4"
                            },
                            {
                                "tag": "字幕社招人内详"
                            },
                            {
                                "tag": "极影字幕社"
                            }
                        ]
                    }
                },
                {
                    "share_dmhy_org": {
                        "magnet": {
                            "url": "magnet:?xt=urn:btih:CYOIXZQ6GG34FIDVNRCM2CCW25NZQYQL&tr=http%3A%2F%2F104.143.10.186%3A8000%2Fannounce&tr=udp%3A%2F%2F104.143.10.186%3A8000%2Fannounce&tr=http%3A%2F%2Ftracker.openbittorrent.com%3A80%2Fannounce&tr=http%3A%2F%2Ftracker3.itzmx.com%3A6961%2Fannounce&tr=http%3A%2F%2Ftracker4.itzmx.com%3A2710%2Fannounce"
                        },
                        "author": "jiaoloveKT",
                        "publish_timestamp": "1712993833",
                        "title": "【极影字幕社】★4月新番 狼与香辛料 行商邂逅贤狼/Ookami to Koushinryou: Merchant Meets the Wise Wolf 第02话 GB 1080P MP4（字幕社招人内详）",
                        "page_link": "http://share.dmhy.org/topics/view/667066_4_Ookami_to_Koushinryou_Merchant_Meets_the_Wise_Wolf_02_GB_1080P_MP4.html",
                        "tags": [
                            {
                                "tag": "1080P"
                            },
                            {
                                "tag": "GB"
                            },
                            {
                                "tag": "MP4"
                            },
                            {
                                "tag": "字幕社招人内详"
                            },
                            {
                                "tag": "极影字幕社"
                            }
                        ]
                    }
                },
                {
                    "share_dmhy_org": {
                        "magnet": {
                            "url": "magnet:?xt=urn:btih:SQL6VDZYJP2NGHOYKZMFAK3ARWDA6F3N&tr=http%3A%2F%2F104.143.10.186%3A8000%2Fannounce&tr=udp%3A%2F%2F104.143.10.186%3A8000%2Fannounce&tr=http%3A%2F%2Ftracker.openbittorrent.com%3A80%2Fannounce&tr=http%3A%2F%2Ftracker3.itzmx.com%3A6961%2Fannounce&tr=http%3A%2F%2Ftracker4.itzmx.com%3A2710%2Fannounce"
                        },
                        "author": "KissSub",
                        "publish_timestamp": "1713052018",
                        "title": "[爱恋&漫猫字幕社][4月新番][狼与香辛料 行商邂逅贤狼][Spice and Wolf][02][720p][MP4][GB][简中]",
                        "page_link": "http://share.dmhy.org/topics/view/667164_4_Spice_and_Wolf_02_720p_MP4_GB.html",
                        "tags": [
                            {
                                "tag": "720P"
                            },
                            {
                                "tag": "GB"
                            },
                            {
                                "tag": "MP4"
                            },
                            {
                                "tag": "爱恋&漫猫字幕社"
                            },
                            {
                                "tag": "简中"
                            }
                        ]
                    }
                },
                {
                    "share_dmhy_org": {
                        "magnet": {
                            "url": "magnet:?xt=urn:btih:MPYZL2PSDM72ZYGDPPYDQM3K4KA4TZAR&tr=http%3A%2F%2F104.143.10.186%3A8000%2Fannounce&tr=udp%3A%2F%2F104.143.10.186%3A8000%2Fannounce&tr=http%3A%2F%2Ftracker.openbittorrent.com%3A80%2Fannounce&tr=http%3A%2F%2Ftracker3.itzmx.com%3A6961%2Fannounce&tr=http%3A%2F%2Ftracker4.itzmx.com%3A2710%2Fannounce"
                        },
                        "author": "KissSub",
                        "publish_timestamp": "1713052044",
                        "title": "[爱恋&漫猫字幕社][4月新番][狼与香辛料 行商邂逅贤狼][Spice and Wolf][02][1080p][MP4][GB][简中]",
                        "page_link": "http://share.dmhy.org/topics/view/667166_4_Spice_and_Wolf_02_1080p_MP4_GB.html",
                        "tags": [
                            {
                                "tag": "1080P"
                            },
                            {
                                "tag": "GB"
                            },
                            {
                                "tag": "MP4"
                            },
                            {
                                "tag": "爱恋&漫猫字幕社"
                            },
                            {
                                "tag": "简中"
                            }
                        ]
                    }
                }
            ]
        },
        {
            "index": "03",
            "resources": [
                {
                    "share_dmhy_org": {
                        "magnet": {
                            "url": "magnet:?xt=urn:btih:3D4UUF2QPKJ3NP22GIXPOWPGVTWJGACM&tr=http%3A%2F%2F104.143.10.186%3A8000%2Fannounce&tr=udp%3A%2F%2F104.143.10.186%3A8000%2Fannounce&tr=http%3A%2F%2Ftracker.openbittorrent.com%3A80%2Fannounce&tr=http%3A%2F%2Ftracker3.itzmx.com%3A6961%2Fannounce&tr=http%3A%2F%2Ftracker4.itzmx.com%3A2710%2Fannounce"
                        },
                        "author": "zhufeng",
                        "publish_timestamp": "1713218965",
                        "title": "【幻之字幕组】狼与香辛料 行商邂逅贤狼 03/狼と香辛料 MERCHANT MEETS THE WISE WOLF - 03 [简中][1080p][HEVC]",
                        "page_link": "http://share.dmhy.org/topics/view/667395_03_MERCHANT_MEETS_THE_WISE_WOLF_-_03_1080p_HEVC.html",
                        "tags": [
                            {
                                "tag": "1080P"
                            },
                            {
                                "tag": "HEVC"
                            },
                            {
                                "tag": "幻之字幕组"
                            },
                            {
                                "tag": "简中"
                            }
                        ]
                    }
                },
                {
                    "share_dmhy_org": {
                        "magnet": {
                            "url": "magnet:?xt=urn:btih:N3BXFFGAKVGE2MI5ULMHWZZNW2KEF5WE&tr=http%3A%2F%2F104.143.10.186%3A8000%2Fannounce&tr=udp%3A%2F%2F104.143.10.186%3A8000%2Fannounce&tr=http%3A%2F%2Ftracker.openbittorrent.com%3A80%2Fannounce&tr=http%3A%2F%2Ftracker3.itzmx.com%3A6961%2Fannounce&tr=http%3A%2F%2Ftracker4.itzmx.com%3A2710%2Fannounce"
                        },
                        "author": "KissSub",
                        "publish_timestamp": "1713554552",
                        "title": "[爱恋&漫猫字幕社][4月新番][狼与香辛料 行商邂逅贤狼][Spice and Wolf][03][720p][MP4][GB][简中]",
                        "page_link": "http://share.dmhy.org/topics/view/667686_4_Spice_and_Wolf_03_720p_MP4_GB.html",
                        "tags": [
                            {
                                "tag": "720P"
                            },
                            {
                                "tag": "GB"
                            },
                            {
                                "tag": "MP4"
                            },
                            {
                                "tag": "爱恋&漫猫字幕社"
                            },
                            {
                                "tag": "简中"
                            }
                        ]
                    }
                },
                {
                    "share_dmhy_org": {
                        "magnet": {
                            "url": "magnet:?xt=urn:btih:PN6TQQZ4BFAD5THSMSQBW6PHT5Z7U44J&tr=http%3A%2F%2F104.143.10.186%3A8000%2Fannounce&tr=udp%3A%2F%2F104.143.10.186%3A8000%2Fannounce&tr=http%3A%2F%2Ftracker.openbittorrent.com%3A80%2Fannounce&tr=http%3A%2F%2Ftracker3.itzmx.com%3A6961%2Fannounce&tr=http%3A%2F%2Ftracker4.itzmx.com%3A2710%2Fannounce"
                        },
                        "author": "KissSub",
                        "publish_timestamp": "1713554564",
                        "title": "[爱恋&漫猫字幕社][4月新番][狼与香辛料 行商邂逅贤狼][Spice and Wolf][03][1080p][MP4][GB][简中]",
                        "page_link": "http://share.dmhy.org/topics/view/667688_4_Spice_and_Wolf_03_1080p_MP4_GB.html",
                        "tags": [
                            {
                                "tag": "1080P"
                            },
                            {
                                "tag": "GB"
                            },
                            {
                                "tag": "MP4"
                            },
                            {
                                "tag": "爱恋&漫猫字幕社"
                            },
                            {
                                "tag": "简中"
                            }
                        ]
                    }
                },
                {
                    "share_dmhy_org": {
                        "magnet": {
                            "url": "magnet:?xt=urn:btih:TBG3KZROPE2HBTIA65WPC7N6P6LX7BUU&tr=http%3A%2F%2F104.143.10.186%3A8000%2Fannounce&tr=udp%3A%2F%2F104.143.10.186%3A8000%2Fannounce&tr=http%3A%2F%2Ftracker.openbittorrent.com%3A80%2Fannounce&tr=http%3A%2F%2Ftracker3.itzmx.com%3A6961%2Fannounce&tr=http%3A%2F%2Ftracker4.itzmx.com%3A2710%2Fannounce"
                        },
                        "author": "KissSub",
                        "publish_timestamp": "1713556653",
                        "title": "[爱恋&漫猫字幕社][4月新番][狼与香辛料 行商邂逅贤狼][Spice and Wolf][03v2][720p][MP4][GB][简中]",
                        "page_link": "http://share.dmhy.org/topics/view/667690_4_Spice_and_Wolf_03v2_720p_MP4_GB.html",
                        "tags": [
                            {
                                "tag": "720P"
                            },
                            {
                                "tag": "GB"
                            },
                            {
                                "tag": "MP4"
                            },
                            {
                                "tag": "爱恋&漫猫字幕社"
                            },
                            {
                                "tag": "简中"
                            }
                        ]
                    }
                }
            ]
        }
    ]
}